{
  "project_info": {
    "project_number": "194732532548",
    "project_id": "whatsapp-backend-84c61",
    "storage_bucket": "whatsapp-backend-84c61.appspot.com"
  },
  "client": [
    {
      "client_info": {
        "mobilesdk_app_id": "1:194732532548:android:cd4fd5b8b3be5b3b17ed11",
        "android_client_info": {
          "package_name": "com.example.flutter_whatsapp_clone"
        }
      },
      "oauth_client": [
        {
          "client_id": "194732532548-kd3kmuekbv703o1dm9pdm8vt62r59tg0.apps.googleusercontent.com",
          "client_type": 3
        }
      ],
      "api_key": [
        {
          "current_key": "AIzaSyBfVSi1KAdi6jiEI7QVUoStmb7QIHGtqks"
        }
      ],
      "services": {
        "appinvite_service": {
          "other_platform_oauth_client": [
            {
              "client_id": "194732532548-kd3kmuekbv703o1dm9pdm8vt62r59tg0.apps.googleusercontent.com",
              "client_type": 3
            }
          ]
        }
      }
    }
  ],
  "configuration_version": "1"
}